xianbao/__init__.py
xianbao/core/BlockDeque.py
xianbao/core/CustomSQLInterface.py
xianbao/core/DatabaseFactory.py
xianbao/core/DatabaseInterface.py
xianbao/core/DatabaseLanguageEnhanced.py
xianbao/core/DictApi.py
xianbao/core/DictData.py
xianbao/core/DtypeConver.py
xianbao/core/HttpSQLiteDatabase.py
xianbao/core/HttpSQLiteProcessQueue.py
xianbao/core/ProcessQueueInterface.py
xianbao/core/QueueFactory.py
xianbao/core/SQLiteDatabase.py
xianbao/core/Task.py
xianbao/core/TaskApi.py
xianbao/core/__init__.py
xianbao/core/ast.py
xianbao/core/context.py
xianbao/service/__init__.py
xianbao/service/auto_scan.py
xianbao/service/consumer_sb.py
xianbao/service/from_ht.py
xianbao/service/ikea_status.py
xianbao/service/process_scan_sb.py
xianbao/service/rpa_backfilling_qk.py
xianbao/service/rpa_backfilling_recong.py
xianbao/service/图像识别生产者.py
xianbao/service/图片识别生成者.py
xianbao/ui/__init__.py
xianbao/ui/backfill_tab.py
xianbao/ui/main_window.py
xianbao/ui/meta_form.py
xianbao/ui/reconciliation_tab.py
xianbao/ui/scan_material_window.py
xianbao/ui/status_visualization.py
xianbao/ui/task_deleter.py
xianbao/ui/task_detail_viewer.py
xianbao/ui/task_editor.py
xianbao/ui/task_table.py
xianbao/ui/timer_manager.py
xianbao/utils/FileScanner.py
xianbao/utils/__init__.py
xianb-2.0.10.dist-info/METADATA
xianb-2.0.10.dist-info/WHEEL
xianb-2.0.10.dist-info/top_level.txt
xianb-2.0.10.dist-info/RECORD
