Metadata-Version: 2.1
Name: xianb
Version: 2.0.10
Summary: 很大的修改，改到颠了，不想干了
Author: jxjiang
Author-email: 723137901@qq.com
Requires-Python: >=3.8
